extract_azuredevops_boards.py
extract_azuredevops_pipelines.py
extract_azuredevops_repos.py
extract_bitbucket_pipelines.py
extract_bitbucket_repos.py
extract_github.py
extract_github_actions.py
extract_gitlab.py
extract_jenkins.py
extract_jira.py
extract_octopus.py
sftp_upload.py
common/__init__.py
common/code_commit_event.py
common/config.json
common/driver.py
common/exceptions.py
common/extract.sh
common/file_manager.py
common/generate_mcp_token.py
common/loader.py
common/parser.py
common/reader.py
common/utils.py
talentsavvy_improveteam-3174.83.dist-info/METADATA
talentsavvy_improveteam-3174.83.dist-info/WHEEL
talentsavvy_improveteam-3174.83.dist-info/entry_points.txt
talentsavvy_improveteam-3174.83.dist-info/top_level.txt
talentsavvy_improveteam-3174.83.dist-info/RECORD
