Metadata-Version: 2.4
Name: talentsavvy-improveteam
Version: 3174.83
Summary: Scripts for data extraction scripts from software development systems
Author: TalentSavvy.com
Classifier: Programming Language :: Python :: 3
Classifier: Programming Language :: Python :: 3.7
Classifier: Programming Language :: Python :: 3.8
Classifier: Programming Language :: Python :: 3.9
Classifier: Programming Language :: Python :: 3.10
Classifier: Programming Language :: Python :: 3.11
Classifier: Operating System :: OS Independent
Requires-Python: >=3.7
Requires-Dist: paramiko
Requires-Dist: pytz
Requires-Dist: python-dateutil
Requires-Dist: pandas
Requires-Dist: requests
Requires-Dist: urllib3
Dynamic: author
Dynamic: classifier
Dynamic: description
Dynamic: description-content-type
Dynamic: requires-dist
Dynamic: requires-python
Dynamic: summary
